.coverage
MANIFEST.in
setup.cfg
setup.py
test_config.ini.sample
ls_s3_logs.egg-info/PKG-INFO
ls_s3_logs.egg-info/SOURCES.txt
ls_s3_logs.egg-info/dependency_links.txt
ls_s3_logs.egg-info/requires.txt
ls_s3_logs.egg-info/top_level.txt
lss3logs/__init__.py
lss3logs/base.py
lss3logs/delete.py
lss3logs/download.py
lss3logs/log_file.py
lss3logs/tests/__init__.py
lss3logs/tests/conf.py
lss3logs/tests/test_lss3logs.py