Metadata-Version: 1.1
Name: ls-s3-logs
Version: 0.1.1
Summary: A library to parse S3 log files.
Home-page: https://github.com/liquid-state/ls-s3-logs
Author: Liquid State Pty Ltd
Author-email: dev@liquid-state.com
License: BSD
Platform: UNKNOWN
Classifier: Topic :: Internet :: WWW/HTTP :: Dynamic Content
Classifier: Intended Audience :: Developers
Classifier: Programming Language :: Python
Classifier: Programming Language :: Python :: 2.7
Classifier: Topic :: Software Development :: Libraries :: Python Modules
Classifier: Development Status :: 4 - Beta
Classifier: Operating System :: OS Independent
